maples_dr/__init__.py
maples_dr/config.py
maples_dr/dataset.py
maples_dr/loader.py
maples_dr/preprocessing.py
maples_dr/quick_api.py
maples_dr/utilities.py
maples_dr-1.0.0.dist-info/LICENSE
maples_dr-1.0.0.dist-info/METADATA
maples_dr-1.0.0.dist-info/WHEEL
maples_dr-1.0.0.dist-info/top_level.txt
maples_dr-1.0.0.dist-info/RECORD
