Metadata-Version: 2.1
Name: maples-dr
Version: 1.0.0
Summary: Utilities python library for the public dataset of retinal structures: MAPLES-DR.
Author-email: Gabriel Lepetit-Aimon <gabriel.lepetit-aimon@polymtl.ca>
Project-URL: Homepage, https://liv4d.github.io/MAPLES-DR/en/
Project-URL: Documentation, https://liv4d.github.io/MAPLES-DR/en/welcome/python_library.html
Project-URL: Source, https://github.com/LIV4D/MAPlES-DR
Requires-Python: >=3.10
License-File: LICENSE
Requires-Dist: numpy
Requires-Dist: Pillow
Requires-Dist: pandas
Requires-Dist: xlrd
Requires-Dist: pyyaml
Requires-Dist: rich
Provides-Extra: dev
Requires-Dist: sphinx; extra == "dev"
Requires-Dist: sphinx-rtd-theme; extra == "dev"
Requires-Dist: sphinx-copybutton; extra == "dev"
Requires-Dist: sphinxcontrib-bibtex; extra == "dev"
Requires-Dist: nbsphinx; extra == "dev"
Requires-Dist: sphinx-intl; extra == "dev"
Requires-Dist: ipython; extra == "dev"
Provides-Extra: examples
Requires-Dist: plotly; extra == "examples"
Requires-Dist: rich; extra == "examples"
Requires-Dist: scikit-learn; extra == "examples"
Requires-Dist: scikit-image; extra == "examples"
Requires-Dist: scipy; extra == "examples"
Requires-Dist: tqdm; extra == "examples"
Requires-Dist: jppype; extra == "examples"
Requires-Dist: irrcac; extra == "examples"
Provides-Extra: test
Requires-Dist: pytest; extra == "test"
